LICENSE
MANIFEST.in
README.md
setup.py
tests/__init__.py
tests/http_response_catcher.py
tests/test_helper.py
tests/controllers/__init__.py
tests/controllers/controller_test_base.py
tests/controllers/test_api_controller.py
wlufqksjez/__init__.py
wlufqksjez/api_helper.py
wlufqksjez/configuration.py
wlufqksjez/decorators.py
wlufqksjez/wlufqksjez_client.py
wlufqksjez.egg-info/PKG-INFO
wlufqksjez.egg-info/SOURCES.txt
wlufqksjez.egg-info/dependency_links.txt
wlufqksjez.egg-info/requires.txt
wlufqksjez.egg-info/top_level.txt
wlufqksjez/controllers/__init__.py
wlufqksjez/controllers/api_controller.py
wlufqksjez/controllers/base_controller.py
wlufqksjez/exceptions/__init__.py
wlufqksjez/exceptions/api_exception.py
wlufqksjez/http/__init__.py
wlufqksjez/http/http_call_back.py
wlufqksjez/http/http_client.py
wlufqksjez/http/http_context.py
wlufqksjez/http/http_method_enum.py
wlufqksjez/http/http_request.py
wlufqksjez/http/http_response.py
wlufqksjez/http/requests_client.py
wlufqksjez/http/auth/__init__.py
wlufqksjez/http/auth/basic_auth.py
wlufqksjez/models/__init__.py
wlufqksjez/models/suite_code_enum.py